pyteller/__init__.py
pyteller/analysis.py
pyteller/benchmark.py
pyteller/core.py
pyteller/data.py
pyteller/evaluation/__init__.py
pyteller/evaluation/metrics.py
pyteller/primitives/__init__.py
pyteller/primitives/estimators.py
pyteller-0.1.0.dist-info/AUTHORS.rst
pyteller-0.1.0.dist-info/LICENSE
pyteller-0.1.0.dist-info/METADATA
pyteller-0.1.0.dist-info/WHEEL
pyteller-0.1.0.dist-info/entry_points.txt
pyteller-0.1.0.dist-info/top_level.txt
pyteller-0.1.0.dist-info/RECORD
