Metadata-Version: 2.1
Name: pyteller
Version: 0.1.0
Summary: Time series forecasting using MLPrimitives
Home-page: https://github.com/signals-dev/pyteller
Author: MIT Data To AI Lab
Author-email: dailabmit@gmail.com
License: MIT license
Keywords: pyteller pyteller pyteller
Platform: UNKNOWN
Classifier: Development Status :: 2 - Pre-Alpha
Classifier: Intended Audience :: Developers
Classifier: License :: OSI Approved :: MIT License
Classifier: Natural Language :: English
Classifier: Programming Language :: Python :: 3
Classifier: Programming Language :: Python :: 3.5
Classifier: Programming Language :: Python :: 3.6
Classifier: Programming Language :: Python :: 3.7
Classifier: Programming Language :: Python :: 3.8
Requires-Python: >=3.5
Requires-Dist: s3fs (<0.5,>=0.2.2)
Requires-Dist: baytune (<0.3,>=0.2.3)
Requires-Dist: mlblocks (<0.4,>=0.3.0)
Requires-Dist: mlprimitives (<0.3,>=0.2.2)
Requires-Dist: mongoengine (<0.17,>=0.16.3)
Requires-Dist: numpy (<1.17,>=1.15.4)
Requires-Dist: pandas (<0.25,>=0.23.4)
Requires-Dist: pymongo (<4,>=3.7.2)
Requires-Dist: scikit-learn (<0.21,>=0.20.1)
Requires-Dist: tabulate (<0.9,>=0.8.3)
Requires-Dist: Keras (<2.4,>=2.1.6)
Provides-Extra: dev
Requires-Dist: bumpversion (>=0.5.3) ; extra == 'dev'
Requires-Dist: pip (>=9.0.1) ; extra == 'dev'
Requires-Dist: watchdog (>=0.8.3) ; extra == 'dev'
Requires-Dist: m2r (<0.3,>=0.2.0) ; extra == 'dev'
Requires-Dist: Sphinx (<3,>=1.7.1) ; extra == 'dev'
Requires-Dist: sphinx-rtd-theme (<0.5,>=0.2.4) ; extra == 'dev'
Requires-Dist: autodocsumm (>=0.1.10) ; extra == 'dev'
Requires-Dist: flake8 (>=3.7.7) ; extra == 'dev'
Requires-Dist: isort (>=4.3.4) ; extra == 'dev'
Requires-Dist: autoflake (>=1.2) ; extra == 'dev'
Requires-Dist: autopep8 (>=1.4.3) ; extra == 'dev'
Requires-Dist: twine (>=1.10.0) ; extra == 'dev'
Requires-Dist: wheel (>=0.30.0) ; extra == 'dev'
Requires-Dist: coverage (>=4.5.1) ; extra == 'dev'
Requires-Dist: tox (>=2.9.1) ; extra == 'dev'
Requires-Dist: pytest (>=3.4.2) ; extra == 'dev'
Requires-Dist: pytest-cov (>=2.6.0) ; extra == 'dev'
Provides-Extra: test
Requires-Dist: pytest (>=3.4.2) ; extra == 'test'
Requires-Dist: pytest-cov (>=2.6.0) ; extra == 'test'
